<Alloy>
	<Window title="Panel Details" id="panelDetails" backButtonTitle="" class="container" navTintColor="#CE1D1C"  >
		<RightNavButton platform="ios" >
	        <View right="0" width="20%">
		         	<ImageView right='10' id="btnDirection" visible="false" width="25" height="25" image="/images/map.png" />
		   		</View>
        </RightNavButton>
		<View id="main" layout="vertical" backgroundColor="#F6F6F6" height="100%" >
		<View layout="horizontal" height="50" width="Ti.UI.FILL" backgroundColor="#DEDEDE" platform="android" > 
				<View left="0" width="20%">
		         	<ImageView left='10' id="btnBack" width="25" height="25" image="/images/btn-back.png" />
		   		</View>
		     	<View width="60%">
		     		<Label height="Ti.UI.SIZE" class='normal_font' textAlign="center">Panel Details</Label>
		     	</View>
		     	<View right="0" width="20%" >
		     		<ImageView right='10' id="btnDirection" visible="false" width="25" height="25" image="/images/map.png" />
		   		</View>
		 </View>
		 <View id="clinicMap" height="200" width="Ti.UI.FILL" >
		 	<ImageView right='10' top='10' id="showFullMap" zIndex="99" width="25" height="25" image="/images/zoom_in.png" /> 
		 </View>
		 		
		 <ScrollView layout="vertical" scrollType="vertical" backgroundColor="#ffffff" height="Ti.UI.FILL" width="Ti.UI.FILL" class="contwfill conthsize" top="0">
 
		 	<View class="box rounded padding wfill hsize vert" bottom="0">
		 		<View class="box rounded wfill horz" backgroundColor="#ffffff" top="0" height="80">
			 		<View width="32%" height="80" onClick="direction2here" layout="vertical">
			 			<ImageView image="/images/map.png" width="40" height="40" top="5" />
			 			<Label class="darkgreyText small_font center" >Direction To Here</Label>
			 		</View>
			 		<View width="1" height="80" backgroundColor="#dfe0e4" />
			 		<View width="32%" height="80" onClick="clickToCall" layout="vertical"  >
			 			<ImageView image="/images/call.png" width="30" height="30" top="5" />
			 			<Label class="darkgreyText small_font center" top="10" >Call</Label>
			 		</View>
			 		<View width="1" height="80" backgroundColor="#dfe0e4" />
			 		<View width="auto" height="80" onClick="addToContact" id="add2contact" layout="vertical" >
			 			<ImageView image="/images/add_to_contact.png" width="35" height="35" top="5" />
			 			<Label class="darkgreyText small_font center"  width="Ti.UI.FILL" top="5">Add To Contact</Label>
			 		</View>
			 	</View>
		 		<View class="wfill hsize vert padding" id="clinicDetailsView">
			 		<Label id="clinicName" class="wfill hsize " top="10" bottom="10"></Label>
 
			 		<Label text="Address" class="wfill hsize bold" />
				 	<Label id="clinicAddress" class="wfill hsize " bottom="10" /> 
				 	
				 	<Label text="Coordinate" class="wfill hsize bold" />
				 	<Label id="clinicLocation" class="wfill hsize"  bottom="10"   />
				 	
				 	<Label text="Telephone/Mobile" class="wfill hsize bold" />
				 	<Label id="clinicTel" class="wfill hsize"  bottom="10"   />
				 	
				 	<Label text="Operation Hours" class="wfill hsize bold" />
				 	<View class="wfill hsize vert" left="0" right="5" bottom="10" id="clinicOper" />
			 	</View>
			 </View>
		 </ScrollView>
		 </View>
	</Window>
</Alloy>